[
    {
        "tipo": "PUBLIC",
        "valor": "public",
        "linea": 1
    },
    {
        "tipo": "CLASS",
        "valor": "class",
        "linea": 1
    },
    {
        "tipo": "ID",
        "valor": "Demo",
        "linea": 1
    },
    {
        "tipo": "LLAVE_IZQ",
        "valor": "{",
        "linea": 1
    },
    {
        "tipo": "PUBLIC",
        "valor": "public",
        "linea": 2
    },
    {
        "tipo": "STATIC",
        "valor": "static",
        "linea": 2
    },
    {
        "tipo": "VOID",
        "valor": "void",
        "linea": 2
    },
    {
        "tipo": "MAIN",
        "valor": "main",
        "linea": 2
    },
    {
        "tipo": "PARENTESIS_IZQ",
        "valor": "(",
        "linea": 2
    },
    {
        "tipo": "STRINGTYPE",
        "valor": "String",
        "linea": 2
    },
    {
        "tipo": "CORCHETE_IZQ",
        "valor": "[",
        "linea": 2
    },
    {
        "tipo": "CORCHETE_DER",
        "valor": "]",
        "linea": 2
    },
    {
        "tipo": "ID",
        "valor": "args",
        "linea": 2
    },
    {
        "tipo": "PARENTESIS_DER",
        "valor": ")",
        "linea": 2
    },
    {
        "tipo": "LLAVE_IZQ",
        "valor": "{",
        "linea": 2
    },
    {
        "tipo": "INT",
        "valor": "int",
        "linea": 3
    },
    {
        "tipo": "ID",
        "valor": "a",
        "linea": 3
    },
    {
        "tipo": "IGUAL",
        "valor": "=",
        "linea": 3
    },
    {
        "tipo": "NUMBER",
        "valor": "5",
        "linea": 3
    },
    {
        "tipo": "POR",
        "valor": "*",
        "linea": 3
    },
    {
        "tipo": "NUMBER",
        "valor": "2",
        "linea": 3
    },
    {
        "tipo": "MAS",
        "valor": "+",
        "linea": 3
    },
    {
        "tipo": "NUMBER",
        "valor": "10",
        "linea": 3
    },
    {
        "tipo": "PUNTOCOMA",
        "valor": ";",
        "linea": 3
    },
    {
        "tipo": "PRINT",
        "valor": "print",
        "linea": 4
    },
    {
        "tipo": "PARENTESIS_IZQ",
        "valor": "(",
        "linea": 4
    },
    {
        "tipo": "ID",
        "valor": "a",
        "linea": 4
    },
    {
        "tipo": "PARENTESIS_DER",
        "valor": ")",
        "linea": 4
    },
    {
        "tipo": "PUNTOCOMA",
        "valor": ";",
        "linea": 4
    },
    {
        "tipo": "IF",
        "valor": "if",
        "linea": 6
    },
    {
        "tipo": "PARENTESIS_IZQ",
        "valor": "(",
        "linea": 6
    },
    {
        "tipo": "ID",
        "valor": "a",
        "linea": 6
    },
    {
        "tipo": "MAYOR",
        "valor": ">",
        "linea": 6
    },
    {
        "tipo": "NUMBER",
        "valor": "15",
        "linea": 6
    },
    {
        "tipo": "PARENTESIS_DER",
        "valor": ")",
        "linea": 6
    },
    {
        "tipo": "LLAVE_IZQ",
        "valor": "{",
        "linea": 6
    },
    {
        "tipo": "PRINT",
        "valor": "print",
        "linea": 7
    },
    {
        "tipo": "PARENTESIS_IZQ",
        "valor": "(",
        "linea": 7
    },
    {
        "tipo": "CADENA",
        "valor": "Es Mayor",
        "linea": 7
    },
    {
        "tipo": "PARENTESIS_DER",
        "valor": ")",
        "linea": 7
    },
    {
        "tipo": "PUNTOCOMA",
        "valor": ";",
        "linea": 7
    },
    {
        "tipo": "LLAVE_DER",
        "valor": "}",
        "linea": 8
    },
    {
        "tipo": "ELSE",
        "valor": "else",
        "linea": 8
    },
    {
        "tipo": "LLAVE_IZQ",
        "valor": "{",
        "linea": 8
    },
    {
        "tipo": "PRINT",
        "valor": "print",
        "linea": 9
    },
    {
        "tipo": "PARENTESIS_IZQ",
        "valor": "(",
        "linea": 9
    },
    {
        "tipo": "CADENA",
        "valor": "Es Menor",
        "linea": 9
    },
    {
        "tipo": "PARENTESIS_DER",
        "valor": ")",
        "linea": 9
    },
    {
        "tipo": "PUNTOCOMA",
        "valor": ";",
        "linea": 9
    },
    {
        "tipo": "LLAVE_DER",
        "valor": "}",
        "linea": 10
    },
    {
        "tipo": "INT",
        "valor": "int",
        "linea": 12
    },
    {
        "tipo": "ID",
        "valor": "cont",
        "linea": 12
    },
    {
        "tipo": "IGUAL",
        "valor": "=",
        "linea": 12
    },
    {
        "tipo": "NUMBER",
        "valor": "3",
        "linea": 12
    },
    {
        "tipo": "PUNTOCOMA",
        "valor": ";",
        "linea": 12
    },
    {
        "tipo": "WHILE",
        "valor": "while",
        "linea": 13
    },
    {
        "tipo": "PARENTESIS_IZQ",
        "valor": "(",
        "linea": 13
    },
    {
        "tipo": "ID",
        "valor": "cont",
        "linea": 13
    },
    {
        "tipo": "MAYOR",
        "valor": ">",
        "linea": 13
    },
    {
        "tipo": "NUMBER",
        "valor": "0",
        "linea": 13
    },
    {
        "tipo": "PARENTESIS_DER",
        "valor": ")",
        "linea": 13
    },
    {
        "tipo": "LLAVE_IZQ",
        "valor": "{",
        "linea": 13
    },
    {
        "tipo": "PRINT",
        "valor": "print",
        "linea": 14
    },
    {
        "tipo": "PARENTESIS_IZQ",
        "valor": "(",
        "linea": 14
    },
    {
        "tipo": "ID",
        "valor": "cont",
        "linea": 14
    },
    {
        "tipo": "PARENTESIS_DER",
        "valor": ")",
        "linea": 14
    },
    {
        "tipo": "PUNTOCOMA",
        "valor": ";",
        "linea": 14
    },
    {
        "tipo": "ID",
        "valor": "cont",
        "linea": 15
    },
    {
        "tipo": "IGUAL",
        "valor": "=",
        "linea": 15
    },
    {
        "tipo": "ID",
        "valor": "cont",
        "linea": 15
    },
    {
        "tipo": "MENOS",
        "valor": "-",
        "linea": 15
    },
    {
        "tipo": "NUMBER",
        "valor": "1",
        "linea": 15
    },
    {
        "tipo": "PUNTOCOMA",
        "valor": ";",
        "linea": 15
    },
    {
        "tipo": "LLAVE_DER",
        "valor": "}",
        "linea": 16
    },
    {
        "tipo": "LLAVE_DER",
        "valor": "}",
        "linea": 17
    },
    {
        "tipo": "LLAVE_DER",
        "valor": "}",
        "linea": 18
    }
]